{
  "dependencies": [
    "@gentleduck/libs"
  ],
  "files": [
    {
      "content": "'use client'\n\nimport { cn } from '@gentleduck/libs/cn'\nimport * as React from 'react'\n\nexport interface AvatarProps extends React.HTMLProps<HTMLImageElement> {\n  fallback?: string\n}\n\nfunction Avatar({ className, fallback, alt, ref, ...props }: AvatarProps) {\n  const [isValid, setIsValid] = React.useState(true)\n\n  return (\n    <picture className={cn('relative size-10 shrink-0 overflow-hidden rounded-full', className)} data-slot=\"avatar\">\n      <img\n        ref={ref}\n        {...props}\n        alt={alt}\n        className={'relative flex h-full w-full shrink-0 overflow-hidden object-cover text-transparent'}\n        data-slot=\"avatar-img\"\n        height={'100%'}\n        onError={() => setIsValid(false)}\n        onLoad={() => setIsValid(true)}\n        width={'100%'}\n      />\n      {!isValid && (\n        <span\n          aria-label={alt}\n          className=\"absolute inset-0 flex h-full w-full items-center justify-center bg-muted\"\n          data-slot=\"avatar-fallback\"\n          role=\"img\">\n          {fallback?.slice(0, 2)}\n        </span>\n      )}\n    </picture>\n  )\n}\n\nexport interface AvatarGroupProps extends React.HTMLProps<HTMLDivElement> {\n  imgs: React.HTMLProps<HTMLImageElement>[]\n  maxVisible?: number\n}\n\nconst AvatarGroup = React.forwardRef<HTMLDivElement, AvatarGroupProps>(\n  ({ imgs, maxVisible = 3, className, ...props }, ref) => {\n    const visibleImgs = imgs.slice(0, maxVisible)\n    const overflowCount = imgs.length > maxVisible ? imgs.length - maxVisible : 0\n\n    return (\n      <div className={cn('-space-x-5 flex items-center', className)} ref={ref} {...props}>\n        {visibleImgs.map(({ className, alt, ...props }) => (\n          <Avatar\n            alt={alt?.slice(0, 2)}\n            className={cn('border-2 border-border', className)}\n            key={props.id}\n            {...props}\n          />\n        ))}\n\n        {/* Display overflow count if necessary */}\n        {overflowCount > 0 && (\n          <div className=\"relative z-10 inline-block\">\n            <div className=\"flex size-10 items-center justify-center rounded-full bg-primary font-medium text-primary-foreground text-sm ring-2 ring-background\">\n              +{overflowCount}\n            </div>\n          </div>\n        )}\n      </div>\n    )\n  },\n)\n\nexport { Avatar, AvatarGroup }\n",
      "path": "avatar/avatar.tsx",
      "target": "components/ui/avatar.tsx",
      "type": "registry:ui"
    },
    {
      "content": "export * from './avatar'\n",
      "path": "avatar/index.ts",
      "target": "components/ui/index.ts",
      "type": "registry:ui"
    }
  ],
  "name": "avatar",
  "root_folder": "avatar",
  "source": "/registry-ui-duckui/src/avatar",
  "type": "registry:ui"
}